config_pkg
