Metadata-Version: 1.1
Name: config-pkg
Version: 1.1.4
Summary: Python Config PKG
Home-page: https://github.com/spacetab-io/configuration-python
Author: Roquie, detrous
Author-email: roquie0@gmail.com, artyom.slobodyan@gmail.com
License: GPL-3.0-only
Download-URL: https://github.com/spacetab-io/configuration-python/archive/1.1.4.tar.gz
Platform: UNKNOWN
Classifier: Environment :: Web Environment
Classifier: Intended Audience :: Developers
Classifier: License :: OSI Approved :: GNU General Public License v3 (GPLv3)
Classifier: Programming Language :: Python :: 3.6
Classifier: Topic :: Software Development :: Libraries :: Python Modules
